df_gallery/__init__.py
df_gallery/cli.py
df_gallery/template.py
df_gallery/thumbnail_server.py
df_gallery-0.2.0.dist-info/METADATA
df_gallery-0.2.0.dist-info/WHEEL
df_gallery-0.2.0.dist-info/entry_points.txt
df_gallery-0.2.0.dist-info/RECORD
