Metadata-Version: 2.3
Name: df-gallery
Version: 0.2.0
Summary: Generate a fast, filterable HTML image gallery from a CSV/Json file. Uses pandas syntax
Project-URL: Homepage, https://github.com/yourname/df-gallery
Project-URL: Issues, https://github.com/yourname/df-gallery/issues
Author: Freddie Lichtenstein
License: MIT
Keywords: Dataframe,data-exploration,df,gallery,html,images,pandas
Classifier: Environment :: Console
Classifier: License :: OSI Approved :: MIT License
Classifier: Operating System :: OS Independent
Classifier: Programming Language :: Python :: 3
Classifier: Programming Language :: Python :: 3 :: Only
Classifier: Topic :: Multimedia :: Graphics
Classifier: Topic :: Utilities
Requires-Python: >=3.10
